google_adk_redis/__init__.py
google_adk_redis/redis_memory_session_service.py
google_adk_redis/version.py
google_adk_redis-0.1.2.dist-info/licenses/LICENSE
google_adk_redis-0.1.2.dist-info/METADATA
google_adk_redis-0.1.2.dist-info/WHEEL
google_adk_redis-0.1.2.dist-info/top_level.txt
google_adk_redis-0.1.2.dist-info/RECORD
