Metadata-Version: 2.4
Name: google-adk-redis
Version: 0.1.2
Summary: Redis-backed session service for Google ADK
Author: BloodBoy21, hucruz
Maintainer: hucruz
License: 
Requires-Python: >=3.9
License-File: LICENSE
Requires-Dist: google-adk>=1.10.0
Requires-Dist: redis>=6.0.0
Requires-Dist: typing-extensions<5,>=4.5
Provides-Extra: dev
Requires-Dist: pytest>=7.0; extra == "dev"
Requires-Dist: pytest-asyncio>=0.21; extra == "dev"
Dynamic: license-file
